marearts_xcolor/__init__.py
marearts_xcolor/_version.py
marearts_xcolor/api.py
marearts_xcolor/color_extractor.py
marearts_xcolor/color_extractor_cy.cpython-310-aarch64-linux-gnu.so
marearts_xcolor/color_extractor_cy.cpython-310-x86_64-linux-gnu.so
marearts_xcolor/color_extractor_cy.cpython-312-x86_64-linux-gnu.so
marearts_xcolor/color_extractor_cy.cpython-39-x86_64-linux-gnu.so
marearts_xcolor/color_extractor_gpu.py
marearts_xcolor/gpu_utils.py
pure_python_version/__init__.py
pure_python_version/api.py
pure_python_version/color_extractor.py
pure_python_version/color_similarity_demo.py
pure_python_version/demo.py
pure_python_version/examples.py
pure_python_version/tests/__init__.py
pure_python_version/tests/run_all_tests.py
pure_python_version/tests/test_basic_functionality.py
pure_python_version/tests/test_color_analysis.py
pure_python_version/tests/test_gpu_support.py
marearts_xcolor-0.0.7.dist-info/LICENSE
marearts_xcolor-0.0.7.dist-info/METADATA
marearts_xcolor-0.0.7.dist-info/WHEEL
marearts_xcolor-0.0.7.dist-info/entry_points.txt
marearts_xcolor-0.0.7.dist-info/top_level.txt
marearts_xcolor-0.0.7.dist-info/RECORD
