Metadata-Version: 2.1
Name: marearts-xcolor
Version: 0.0.7
Summary: Advanced color extraction and similarity analysis toolkit
Home-page: https://github.com/marearts/marearts-xcolor
Author: MareArts
Author-email: contact@marearts.com
License: UNKNOWN
Project-URL: Bug Reports, https://github.com/marearts/marearts-xcolor/issues
Project-URL: Source, https://github.com/marearts/marearts-xcolor
Project-URL: Documentation, https://github.com/marearts/marearts-xcolor#readme
Keywords: color extraction,color analysis,image processing,computer vision,color similarity,dominant colors,color palette,k-means clustering,LAB color space,brand colors
Platform: UNKNOWN
Classifier: Development Status :: 5 - Production/Stable
Classifier: Intended Audience :: Developers
Classifier: Topic :: Multimedia :: Graphics
Classifier: Topic :: Scientific/Engineering :: Image Processing
Classifier: Topic :: Software Development :: Libraries :: Python Modules
Classifier: License :: OSI Approved :: MIT License
Classifier: Programming Language :: Python :: 3
Classifier: Programming Language :: Python :: 3.9
Classifier: Programming Language :: Python :: 3.10
Classifier: Programming Language :: Python :: 3.11
Classifier: Programming Language :: Python :: 3.12
Classifier: Operating System :: OS Independent
Requires-Python: >=3.9
License-File: LICENSE
Requires-Dist: opencv-python==4.10.0.84
Requires-Dist: scikit-learn>=1.0.0
Requires-Dist: pillow>=8.0.0
Requires-Dist: matplotlib>=3.5.0
Requires-Dist: scipy>=1.7.0
Requires-Dist: numpy==1.23.5; python_version < "3.12"
Requires-Dist: numpy==1.26.0; python_version >= "3.12"
Provides-Extra: dev
Requires-Dist: pytest>=6.0; extra == "dev"
Requires-Dist: pytest-cov>=2.0; extra == "dev"
Requires-Dist: black>=21.0; extra == "dev"
Requires-Dist: flake8>=3.8; extra == "dev"
Requires-Dist: cython>=0.29.21; extra == "dev"
